LICENSE
MANIFEST.in
README.md
requirements.txt
setup.py
test-requirements.txt
docker/machine/__init__.py
docker/machine/constants.py
docker/machine/driver_description.py
docker/machine/errors.py
docker/machine/version.py
docker/machine/cli/__init__.py
docker/machine/cli/client.py
docker/machine/cli/driver_config.py
docker/machine/cli/machine.py
docker/machine/cli/tupperware.py
docker/machine/cli/utils.py
docker_machine_py.egg-info/PKG-INFO
docker_machine_py.egg-info/SOURCES.txt
docker_machine_py.egg-info/dependency_links.txt
docker_machine_py.egg-info/not-zip-safe
docker_machine_py.egg-info/requires.txt
docker_machine_py.egg-info/top_level.txt
tests/__init__.py
tests/integration/machine_test.py
tests/unit/cli_test.py