Metadata-Version: 1.1
Name: docker-machine-py
Version: 0.2.0
Summary: Python wrapper for Docker Machine.
Home-page: https://github.com/jgrowl/docker-machine-py/
Author: UNKNOWN
Author-email: UNKNOWN
License: UNKNOWN
Platform: UNKNOWN
Classifier: Development Status :: 4 - Beta
Classifier: Environment :: Other Environment
Classifier: Intended Audience :: Developers
Classifier: Operating System :: OS Independent
Classifier: Programming Language :: Python
Classifier: Programming Language :: Python :: 2.6
Classifier: Programming Language :: Python :: 2.7
Classifier: Topic :: Utilities
Classifier: License :: OSI Approved :: Apache Software License
